quarktorch/__init__.py
quarktorch/core.py
quarktorch/functions.py
quarktorch-0.0.1.dist-info/METADATA
quarktorch-0.0.1.dist-info/WHEEL
quarktorch-0.0.1.dist-info/RECORD
