Metadata-Version: 2.3
Name: quarktorch
Version: 0.0.1
Summary: The smallest torch in the ML universe.
Author: SyJarvis
Author-email: 1755115828@qq.com
Requires-Python: >=3.8
Classifier: Programming Language :: Python :: 3
Classifier: Programming Language :: Python :: 3.8
Classifier: Programming Language :: Python :: 3.9
Classifier: Programming Language :: Python :: 3.10
Classifier: Programming Language :: Python :: 3.11
Classifier: Programming Language :: Python :: 3.12
Classifier: Programming Language :: Python :: 3.13
